{
  "en": {
    "homepage": {
      "meta": {
        "title": "ACF — Agentic Commerce Framework®"
      },
      "nav": {
        "logoAbbr": "ACF",
        "logoName": "Agentic Commerce Framework®",
        "logoSubtitle": "Global Standard for AI Governance",
        "theStandard": "The Standard",
        "acfScore": "ACF Score",
        "acfControl": "ACF Control",
        "acfCertification": "ACF Certification",
        "regionLabel": "GLOBAL | EN",
        "partners": "Partners",
        "requestAssessment": "Request Assessment"
      },
      "megaMenu": {
        "framework": "Framework",
        "products": "Products",
        "resources": "Resources",
        "aboutAcf": "About ACF",
        "partners": "Partners",
        "partnerAccess": "Partner Access",
        "partnerLogin": "Partner Login",
        "applyToBecome": "Apply to become Partner",
        "contact": "Contact",
        "frameworkPanel": {
          "title": "ACF Standard →",
          "description": "The definitive governance methodology for agentic systems in commercial environments.",
          "architectureGroup": "Architecture",
          "fourPrinciples": "4 Founding Principles",
          "fourLayers": "4 Operational Layers",
          "fourMaturity": "4 Maturity Levels",
          "methodologyGroup": "Methodology",
          "eightModules": "8 Implementation Modules",
          "agenticConstitution": "Agentic Constitution",
          "ddaRoleFramework": "DDA Role Framework",
          "killSwitchProtocol": "Kill Switch Protocol",
          "featured": "FEATURED",
          "downloadWhitePaper": "Download the ACF White Paper",
          "whitePaperDesc": "Full specification — free for registered users.",
          "v1Release": "ACF v1.0 — February 2026",
          "v1ReleaseDesc": "Official release. What's new in the framework."
        },
        "productsPanel": {
          "title": "Products →",
          "description": "Three tools operationalizing the ACF Standard across your organization.",
          "diagnosticGroup": "Diagnostic",
          "acfScoreSovereignty": "ACF Score — Sovereignty Metric",
          "scoringMethodology": "Scoring Methodology",
          "sixGovernanceAxes": "6 Governance Axes",
          "saasGroup": "SaaS Platform",
          "acfControlDashboard": "ACF Control — Governance Dashboard",
          "eighteenKpis": "18 Sovereignty KPIs",
          "adaptiveGating": "Adaptive Gating System",
          "certificationGroup": "Certification",
          "certificationProgram": "ACF Certification Program",
          "certificationLevels": "Certification Levels",
          "auditProcess": "Audit Process"
        },
        "resourcesPanel": {
          "title": "Resources →",
          "description": "Governance insights, research and technical documentation.",
          "latestInsights": "Latest Insights",
          "euAiAct": "EU AI Act & Agentic Systems",
          "ddaExplained": "The DDA Role Explained",
          "killSwitchDesign": "Designing a 3-Level Kill Switch",
          "documentationGroup": "Documentation",
          "technicalSpecs": "Technical Specifications",
          "researchPapers": "Research Papers",
          "acfAcademy": "ACF Academy"
        },
        "aboutPanel": {
          "title": "About ACF →",
          "description": "The story, mission, and legal protection behind the Agentic Commerce Framework®.",
          "whoWeAre": "Who We Are",
          "vincentDorange": "Vincent DORANGE — Creator",
          "missionValues": "Mission & Values",
          "legalProtection": "Legal Protection (INPI)",
          "howWeWork": "How We Work",
          "practitionerNetwork": "Practitioner Network",
          "auditCertification": "Audit & Certification",
          "contactUs": "Contact Us",
          "registered": "REGISTERED",
          "inpiProtected": "INPI Protected — Loi n° 2018-670",
          "inpiDesc": "ACF® is a registered trademark. All methodology and tools are legally protected."
        },
        "partnersPanel": {
          "title": "Partners →",
          "description": "Join the ACF Practitioner network and offer governance services to your clients.",
          "partnerPortal": "Partner Portal",
          "loginToPortal": "Login to Partner Portal",
          "dashboardTools": "Dashboard & Tools",
          "trainingMaterials": "Training Materials",
          "practitionerToolkit": "ACF Practitioner Toolkit",
          "becomePartner": "Become a Partner",
          "applyToJoin": "Apply to Join",
          "partnerTiers": "Partner Tiers",
          "getCertifiedFirst": "Get ACF Certified First"
        }
      },
      "hero": {
        "titleLine1": "The Global Standard for",
        "typedWords": ["Governance", "Sovereignty", "Intelligence", "Commerce"],
        "description": "The Agentic Commerce Framework® (ACF) is the definitive governance methodology for deploying, supervising, and controlling autonomous agentic systems in commercial environments.",
        "ctaPrimary": "Request a Governance Assessment →",
        "ctaSecondary": "Read the Standard",
        "stat1Value": "4",
        "stat1Label": "Founding Principles",
        "stat2Value": "8",
        "stat2Label": "Implementation Modules",
        "stat3Value": "18",
        "stat3Label": "Sovereignty KPIs",
        "stat4Value": "17",
        "stat4Label": "Proprietary Tools",
        "orbTitle": "ACF®",
        "orbSubtitle": "Standard",
        "satelliteScoreName": "ACF Score",
        "satelliteScoreDesc": "Sovereignty Metric",
        "satelliteControlName": "ACF Control",
        "satelliteControlDesc": "Governance SaaS",
        "satelliteCertName": "Certification",
        "satelliteCertDesc": "Attestation",
        "satellitePartnersName": "Partners",
        "satellitePartnersDesc": "Practitioners"
      },
      "statsBar": {
        "stat1Value": "4",
        "stat1Label": "Operational Layers",
        "stat2Value": "18",
        "stat2Label": "Sovereignty KPIs",
        "stat3Value": "17",
        "stat3Label": "Proprietary Tools",
        "stat4Value": "100",
        "stat4Suffix": "%",
        "stat4Label": "Human Sovereignty"
      },
      "principles": {
        "eyebrow": "// Architecture",
        "title": "4 Founding Principles",
        "description": "Four immutable axioms defining the boundary between human authority and autonomous agent execution.",
        "principle1Label": "PRINCIPLE",
        "principle1Title": "Séparation Décision / Exécution",
        "principle1Desc": "No autonomous agent defines its own objectives. Humans define the ends; agents execute exclusively within the defined perimeter. Technically enforced — not a policy, a constraint.",
        "principle1Tag": "SOVEREIGNTY",
        "principle2Label": "PRINCIPLE",
        "principle2Title": "Zones Non Délégables",
        "principle2Desc": "Certain decisions are structurally, ethically, or legally non-automatable. The non-delegable zone is formally defined and technically locked — never configurable by agents themselves.",
        "principle2Tag": "PROTECTION",
        "principle3Label": "PRINCIPLE",
        "principle3Title": "Traçabilité & Interruptibilité",
        "principle3Desc": "Every agent decision is fully traceable, explainable, and stoppable at any time. Three-level kill switch: module stop (<10s), agent stop (<30s), emergency (<60s). Complete auditable log chain, always.",
        "principle3Tag": "CONTROL",
        "principle4Label": "PRINCIPLE",
        "principle4Title": "Gouvernance Vivante",
        "principle4Desc": "Any agentic autonomy requires active, permanent, evolving governance — with dedicated roles (DDA), regular review rituals, and recurring independent audits. Governance is a continuous practice, not a document.",
        "principle4Tag": "CONTINUITY"
      },
      "layers": {
        "eyebrow": "// Structure",
        "title": "4 Operational Layers",
        "description": "A hierarchical architecture from strategic governance to real-time execution supervision.",
        "layer1Num": "LAYER_01",
        "layer1Title": "Governance & Sovereignty",
        "layer1Desc": "Sovereignty charter, governance committee, RACI matrix, non-delegable zone map.",
        "layer2Num": "LAYER_02",
        "layer2Title": "Decision Policy",
        "layer2Desc": "Weighted objectives, arbitration rules, escalation thresholds, regulatory constraints.",
        "layer3Num": "LAYER_03",
        "layer3Title": "Agent System",
        "layer3Desc": "Explicit mandate per agent, interaction perimeter, autonomy level, 5-category taxonomy.",
        "layer4Num": "LAYER_04",
        "layer4Title": "Execution & Supervision",
        "layer4Desc": "Adaptive gating matrix, multi-level alerts, 18 sovereignty KPIs, live dashboards."
      },
      "maturity": {
        "eyebrow": "// Progression",
        "title": "4 Agentic Maturity Levels",
        "description": "ACF classifies systems by autonomy level. Level 2 is the recommended deployment target.",
        "level0Num": "LEVEL_0",
        "level0Name": "Classical Automation",
        "level0Risk": "Very Low Risk",
        "level0Desc": "Fixed rules, no ML. Human intervention for any modification.",
        "level1Num": "LEVEL_1",
        "level1Name": "Assisted Agents",
        "level1Risk": "Low Risk",
        "level1Desc": "Agents analyze and recommend. Every final decision remains with a human.",
        "level2Num": "LEVEL_2",
        "level2Name": "Governed Agents",
        "level2Risk": "Moderate Risk",
        "level2Desc": "Agents decide within strict governance. Non-delegable zones locked.",
        "level2Badge": "★ Recommended Target",
        "level3Num": "LEVEL_3",
        "level3Name": "Supervised Autonomous",
        "level3Risk": "High Risk",
        "level3Desc": "Agents decide and learn. Maximum governance. For mature organizations only."
      },
      "hexPath": {
        "eyebrow": "// Methodology",
        "title": "8 Implementation Modules",
        "description": "A sequential path deployed progressively over 6–18 months. Each module builds on the previous.",
        "mod01Num": "MOD_01",
        "mod01Name": "Sovereignty Diagnostic",
        "mod01Desc": "Sovereignty Score calculation. Risk zone mapping.",
        "mod02Num": "MOD_02",
        "mod02Name": "Decision Mapping",
        "mod02Desc": "Criticality Matrix. Non-delegable zones.",
        "mod03Num": "MOD_03",
        "mod03Name": "Agentic Constitution",
        "mod03Desc": "9 articles. Signed by governance committee.",
        "mod04Num": "MOD_04",
        "mod04Name": "Agent System Design",
        "mod04Desc": "Mandate sheets, interaction perimeters.",
        "mod05Num": "MOD_05",
        "mod05Name": "Security & Reversibility",
        "mod05Desc": "Sandboxing, reversibility plan. Kill switch design.",
        "mod06Num": "MOD_06",
        "mod06Name": "Continuous Governance",
        "mod06Desc": "Monthly reviews. Annual compliance audit.",
        "mod07Num": "MOD_07",
        "mod07Name": "Implementation Roadmap",
        "mod07Desc": "5-phase progressive deployment.",
        "mod08Num": "MOD_08",
        "mod08Name": "Crisis Management",
        "mod08Desc": "3-level incidents. Kill switch drills."
      },
      "video": {
        "eyebrow": "// Why ACF",
        "title": "Governance Cannot Wait.\nAgents Already Decide.",
        "description1": "In 2026, autonomous agents are already executing decisions in commercial environments — setting prices, qualifying leads, processing claims, managing contracts. Most organizations have no framework to govern them.",
        "description2": "ACF was created to fill that void — before a governance failure becomes a legal, financial, or reputational crisis.",
        "quote": "\"The question is no longer whether to deploy agents. It is how to deploy them without surrendering your sovereignty.\"",
        "quoteAuthor": "— Vincent DORANGE, Creator of the ACF Standard",
        "thumbnailBadge": "ACF — FOUNDER MESSAGE",
        "thumbnailName": "Vincent DORANGE",
        "thumbnailRole": "Creator, Agentic Commerce Framework®",
        "duration": "3:09",
        "stat1Value": "2026",
        "stat1Label": "Official Release",
        "stat2Value": "45p",
        "stat2Label": "Full Documentation",
        "stat3Value": "INPI",
        "stat3Label": "Legally Protected",
        "videoModalPlaceholder": "VIDEO PLACEHOLDER",
        "videoModalTitle": "Upload your video to enable playback",
        "videoModalDesc": "Replace this modal with a YouTube or Vimeo embed URL in the code"
      },
      "products": {
        "eyebrow": "// Ecosystem",
        "title": "The ACF Ecosystem",
        "description": "Three complementary products operationalizing the ACF Standard.",
        "score": {
          "label": "DIAGNOSTIC TOOL",
          "title": "ACF Score",
          "description": "Proprietary Sovereignty Score measuring your decisional independence across 6 governance dimensions.",
          "feat1": "Composite Sovereignty Score metric",
          "feat2": "6-axis radar visualization",
          "feat3": "Personalized action plan per axis",
          "link": "Measure your Score →"
        },
        "control": {
          "label": "SAAS PLATFORM",
          "title": "ACF Control",
          "description": "Real-time governance dashboard monitoring your 18 Sovereignty KPIs with adaptive gating and automated escalation.",
          "feat1": "18 KPIs across 6 governance axes",
          "feat2": "Adaptive gating with human escalation",
          "feat3": "Tamper-evident audit logs",
          "link": "Discover ACF Control →"
        },
        "certification": {
          "label": "INDEPENDENT ATTESTATION",
          "title": "ACF Certification",
          "description": "Independent certification attesting compliance with the ACF governance standard. Publicly verifiable.",
          "feat1": "Level 1, 2, and 3 certification paths",
          "feat2": "Publicly verifiable badge",
          "feat3": "Annual renewal + continuous monitoring",
          "link": "Get Certified →"
        }
      },
      "blog": {
        "eyebrow": "// Insights",
        "title": "Latest from the ACF Blog",
        "description": "Governance insights, framework updates, and agentic intelligence research.",
        "article1": {
          "category": "AI REGULATION",
          "title": "How the EU AI Act Applies to Agentic Systems in 2026",
          "excerpt": "The AI Act's risk-based approach creates specific obligations for autonomous agents. Here's what ACF Level 2 governance covers.",
          "date": "2026-02-15",
          "readMore": "Read →"
        },
        "article2": {
          "category": "GOVERNANCE",
          "title": "The DDA: Why Every AI-Native Company Needs a Delegated Decision Agent Officer",
          "excerpt": "The DDA is the legal guardian of your autonomous agents. How to create and empower this critical role.",
          "date": "2026-02-08",
          "readMore": "Read →"
        },
        "article3": {
          "category": "TECHNICAL",
          "title": "Designing a Three-Level Kill Switch for Autonomous Agent Systems",
          "excerpt": "An effective kill switch is not a single button. ACF specifies three interrupt levels with defined response times.",
          "date": "2026-01-29",
          "readMore": "Read →"
        },
        "viewAll": "View All Articles →"
      },
      "cta": {
        "eyebrow": "// Next Step",
        "watermark": "ACF®",
        "title": "Ready to Govern Your\nAgentic Systems?",
        "description": "Request a governance assessment and discover your current Sovereignty Score.",
        "ctaPrimary": "Request a Governance Assessment →",
        "ctaSecondary": "Become an ACF Partner"
      },
      "aiWidget": {
        "buttonLabel": "Ask ACF Agent",
        "buttonStatus": "AI GOVERNANCE · ONLINE",
        "modalBeta": "BETA",
        "modalTitle": "Ask ACF",
        "modalSubtitle": "A chatbot answering questions based on the ACF Standard and governance insights",
        "inputPlaceholder": "Ask about ACF governance...",
        "trendingLabel": "TRENDING QUESTIONS",
        "question1": "What is the ACF Standard?",
        "question2": "How to get ACF certified?",
        "question3": "What is the DDA role?",
        "question4": "What is the Sovereignty Score?",
        "question5": "The 4 Founding Principles?",
        "disclaimer": "AI experiment. Responses based on ACF Standard documentation.",
        "disclaimerLink": "See More"
      },
      "footer": {
        "logoAbbr": "ACF",
        "logoName": "Agentic Commerce Framework®",
        "logoSubtitle": "Global Standard for AI Governance",
        "description": "The definitive governance standard for organizations deploying autonomous agentic systems. Protected — Loi n° 2018-670.",
        "frameworkTitle": "Framework",
        "frameworkLinks": {
          "theStandard": "The Standard",
          "methodology": "Methodology",
          "research": "Research",
          "acfCertification": "ACF Certification"
        },
        "productsTitle": "Products",
        "productsLinks": {
          "acfScore": "ACF Score",
          "acfControl": "ACF Control",
          "certification": "Certification",
          "academy": "Academy"
        },
        "organizationTitle": "Organization",
        "organizationLinks": {
          "partnerPortal": "Partner Portal",
          "about": "About",
          "contact": "Contact",
          "legal": "Legal"
        },
        "copyright": "© 2026 Agentic Commerce Framework® — Vincent DORANGE. All rights reserved. Registered INPI.",
        "privacy": "Privacy",
        "terms": "Terms",
        "cookies": "Cookies"
      }
    }
  },
  "fr": {
    "homepage": {
      "meta": {
        "title": "ACF — Agentic Commerce Framework®"
      },
      "nav": {
        "logoAbbr": "ACF",
        "logoName": "Agentic Commerce Framework®",
        "logoSubtitle": "Standard mondial pour la gouvernance de l'IA",
        "theStandard": "Le Standard",
        "acfScore": "ACF Score",
        "acfControl": "ACF Control",
        "acfCertification": "Certification ACF",
        "regionLabel": "GLOBAL | FR",
        "partners": "Partenaires",
        "requestAssessment": "Demander une évaluation"
      },
      "megaMenu": {
        "framework": "Framework",
        "products": "Produits",
        "resources": "Ressources",
        "aboutAcf": "À propos d'ACF",
        "partners": "Partenaires",
        "partnerAccess": "Accès partenaire",
        "partnerLogin": "Connexion partenaire",
        "applyToBecome": "Devenir partenaire",
        "contact": "Contact",
        "frameworkPanel": {
          "title": "Standard ACF →",
          "description": "La méthodologie de gouvernance de référence pour les systèmes agentiques en environnement commercial.",
          "architectureGroup": "Architecture",
          "fourPrinciples": "4 Principes fondateurs",
          "fourLayers": "4 Couches opérationnelles",
          "fourMaturity": "4 Niveaux de maturité",
          "methodologyGroup": "Méthodologie",
          "eightModules": "8 Modules d'implémentation",
          "agenticConstitution": "Constitution agentique",
          "ddaRoleFramework": "Cadre du rôle DDA",
          "killSwitchProtocol": "Protocole Kill Switch",
          "featured": "À LA UNE",
          "downloadWhitePaper": "Télécharger le livre blanc ACF",
          "whitePaperDesc": "Spécification complète — gratuit pour les utilisateurs enregistrés.",
          "v1Release": "ACF v1.0 — Février 2026",
          "v1ReleaseDesc": "Version officielle. Les nouveautés du framework."
        },
        "productsPanel": {
          "title": "Produits →",
          "description": "Trois outils opérationnalisant le Standard ACF au sein de votre organisation.",
          "diagnosticGroup": "Diagnostic",
          "acfScoreSovereignty": "ACF Score — Métrique de souveraineté",
          "scoringMethodology": "Méthodologie de scoring",
          "sixGovernanceAxes": "6 Axes de gouvernance",
          "saasGroup": "Plateforme SaaS",
          "acfControlDashboard": "ACF Control — Tableau de bord de gouvernance",
          "eighteenKpis": "18 KPIs de souveraineté",
          "adaptiveGating": "Système de gating adaptatif",
          "certificationGroup": "Certification",
          "certificationProgram": "Programme de certification ACF",
          "certificationLevels": "Niveaux de certification",
          "auditProcess": "Processus d'audit"
        },
        "resourcesPanel": {
          "title": "Ressources →",
          "description": "Analyses de gouvernance, recherche et documentation technique.",
          "latestInsights": "Dernières analyses",
          "euAiAct": "AI Act européen et systèmes agentiques",
          "ddaExplained": "Le rôle du DDA expliqué",
          "killSwitchDesign": "Concevoir un Kill Switch à 3 niveaux",
          "documentationGroup": "Documentation",
          "technicalSpecs": "Spécifications techniques",
          "researchPapers": "Articles de recherche",
          "acfAcademy": "ACF Academy"
        },
        "aboutPanel": {
          "title": "À propos d'ACF →",
          "description": "L'histoire, la mission et la protection juridique derrière l'Agentic Commerce Framework®.",
          "whoWeAre": "Qui nous sommes",
          "vincentDorange": "Vincent DORANGE — Créateur",
          "missionValues": "Mission et valeurs",
          "legalProtection": "Protection juridique (INPI)",
          "howWeWork": "Comment nous travaillons",
          "practitionerNetwork": "Réseau de praticiens",
          "auditCertification": "Audit et certification",
          "contactUs": "Contactez-nous",
          "registered": "ENREGISTRÉ",
          "inpiProtected": "Protégé INPI — Loi n° 2018-670",
          "inpiDesc": "ACF® est une marque déposée. Toute la méthodologie et les outils sont juridiquement protégés."
        },
        "partnersPanel": {
          "title": "Partenaires →",
          "description": "Rejoignez le réseau de praticiens ACF et proposez des services de gouvernance à vos clients.",
          "partnerPortal": "Portail partenaire",
          "loginToPortal": "Connexion au portail partenaire",
          "dashboardTools": "Tableau de bord et outils",
          "trainingMaterials": "Supports de formation",
          "practitionerToolkit": "Boîte à outils du praticien ACF",
          "becomePartner": "Devenir partenaire",
          "applyToJoin": "Postuler",
          "partnerTiers": "Niveaux partenaires",
          "getCertifiedFirst": "Obtenez d'abord la certification ACF"
        }
      },
      "hero": {
        "titleLine1": "Le standard mondial pour la",
        "typedWords": ["Gouvernance", "Souveraineté", "Intelligence", "Commerce"],
        "description": "L'Agentic Commerce Framework® (ACF) est la méthodologie de gouvernance de référence pour le déploiement, la supervision et le contrôle des systèmes agentiques autonomes en environnement commercial.",
        "ctaPrimary": "Demander une évaluation de gouvernance →",
        "ctaSecondary": "Lire le Standard",
        "stat1Value": "4",
        "stat1Label": "Principes fondateurs",
        "stat2Value": "8",
        "stat2Label": "Modules d'implémentation",
        "stat3Value": "18",
        "stat3Label": "KPIs de souveraineté",
        "stat4Value": "17",
        "stat4Label": "Outils propriétaires",
        "orbTitle": "ACF®",
        "orbSubtitle": "Standard",
        "satelliteScoreName": "ACF Score",
        "satelliteScoreDesc": "Métrique de souveraineté",
        "satelliteControlName": "ACF Control",
        "satelliteControlDesc": "SaaS de gouvernance",
        "satelliteCertName": "Certification",
        "satelliteCertDesc": "Attestation",
        "satellitePartnersName": "Partenaires",
        "satellitePartnersDesc": "Praticiens"
      },
      "statsBar": {
        "stat1Value": "4",
        "stat1Label": "Couches opérationnelles",
        "stat2Value": "18",
        "stat2Label": "KPIs de souveraineté",
        "stat3Value": "17",
        "stat3Label": "Outils propriétaires",
        "stat4Value": "100",
        "stat4Suffix": "%",
        "stat4Label": "Souveraineté humaine"
      },
      "principles": {
        "eyebrow": "// Architecture",
        "title": "4 Principes fondateurs",
        "description": "Quatre axiomes immuables définissant la frontière entre l'autorité humaine et l'exécution autonome des agents.",
        "principle1Label": "PRINCIPE",
        "principle1Title": "Séparation Décision / Exécution",
        "principle1Desc": "Aucun agent autonome ne définit ses propres objectifs. Les humains définissent les fins ; les agents exécutent exclusivement dans le périmètre défini. Techniquement imposé — pas une politique, une contrainte.",
        "principle1Tag": "SOUVERAINETÉ",
        "principle2Label": "PRINCIPE",
        "principle2Title": "Zones Non Délégables",
        "principle2Desc": "Certaines décisions sont structurellement, éthiquement ou légalement non automatisables. La zone non délégable est formellement définie et techniquement verrouillée — jamais configurable par les agents eux-mêmes.",
        "principle2Tag": "PROTECTION",
        "principle3Label": "PRINCIPE",
        "principle3Title": "Traçabilité & Interruptibilité",
        "principle3Desc": "Chaque décision d'agent est entièrement traçable, explicable et arrêtable à tout moment. Kill switch à trois niveaux : arrêt module (<10s), arrêt agent (<30s), urgence (<60s). Chaîne de logs auditable complète, toujours.",
        "principle3Tag": "CONTRÔLE",
        "principle4Label": "PRINCIPE",
        "principle4Title": "Gouvernance Vivante",
        "principle4Desc": "Toute autonomie agentique nécessite une gouvernance active, permanente et évolutive — avec des rôles dédiés (DDA), des rituels de revue réguliers et des audits indépendants récurrents. La gouvernance est une pratique continue, pas un document.",
        "principle4Tag": "CONTINUITÉ"
      },
      "layers": {
        "eyebrow": "// Structure",
        "title": "4 Couches opérationnelles",
        "description": "Une architecture hiérarchique de la gouvernance stratégique à la supervision d'exécution en temps réel.",
        "layer1Num": "LAYER_01",
        "layer1Title": "Gouvernance & Souveraineté",
        "layer1Desc": "Charte de souveraineté, comité de gouvernance, matrice RACI, cartographie des zones non délégables.",
        "layer2Num": "LAYER_02",
        "layer2Title": "Politique décisionnelle",
        "layer2Desc": "Objectifs pondérés, règles d'arbitrage, seuils d'escalade, contraintes réglementaires.",
        "layer3Num": "LAYER_03",
        "layer3Title": "Système d'agents",
        "layer3Desc": "Mandat explicite par agent, périmètre d'interaction, niveau d'autonomie, taxonomie à 5 catégories.",
        "layer4Num": "LAYER_04",
        "layer4Title": "Exécution & Supervision",
        "layer4Desc": "Matrice de gating adaptatif, alertes multi-niveaux, 18 KPIs de souveraineté, tableaux de bord en temps réel."
      },
      "maturity": {
        "eyebrow": "// Progression",
        "title": "4 Niveaux de maturité agentique",
        "description": "ACF classifie les systèmes par niveau d'autonomie. Le niveau 2 est la cible de déploiement recommandée.",
        "level0Num": "LEVEL_0",
        "level0Name": "Automatisation classique",
        "level0Risk": "Risque très faible",
        "level0Desc": "Règles fixes, pas de ML. Intervention humaine pour toute modification.",
        "level1Num": "LEVEL_1",
        "level1Name": "Agents assistés",
        "level1Risk": "Risque faible",
        "level1Desc": "Les agents analysent et recommandent. Chaque décision finale reste humaine.",
        "level2Num": "LEVEL_2",
        "level2Name": "Agents gouvernés",
        "level2Risk": "Risque modéré",
        "level2Desc": "Les agents décident dans un cadre de gouvernance strict. Zones non délégables verrouillées.",
        "level2Badge": "★ Cible recommandée",
        "level3Num": "LEVEL_3",
        "level3Name": "Autonomes supervisés",
        "level3Risk": "Risque élevé",
        "level3Desc": "Les agents décident et apprennent. Gouvernance maximale. Réservé aux organisations matures."
      },
      "hexPath": {
        "eyebrow": "// Méthodologie",
        "title": "8 Modules d'implémentation",
        "description": "Un parcours séquentiel déployé progressivement sur 6 à 18 mois. Chaque module s'appuie sur le précédent.",
        "mod01Num": "MOD_01",
        "mod01Name": "Diagnostic de souveraineté",
        "mod01Desc": "Calcul du Score de souveraineté. Cartographie des zones de risque.",
        "mod02Num": "MOD_02",
        "mod02Name": "Cartographie décisionnelle",
        "mod02Desc": "Matrice de criticité. Zones non délégables.",
        "mod03Num": "MOD_03",
        "mod03Name": "Constitution agentique",
        "mod03Desc": "9 articles. Signée par le comité de gouvernance.",
        "mod04Num": "MOD_04",
        "mod04Name": "Conception du système d'agents",
        "mod04Desc": "Fiches de mandat, périmètres d'interaction.",
        "mod05Num": "MOD_05",
        "mod05Name": "Sécurité & Réversibilité",
        "mod05Desc": "Sandboxing, plan de réversibilité. Conception du kill switch.",
        "mod06Num": "MOD_06",
        "mod06Name": "Gouvernance continue",
        "mod06Desc": "Revues mensuelles. Audit de conformité annuel.",
        "mod07Num": "MOD_07",
        "mod07Name": "Feuille de route d'implémentation",
        "mod07Desc": "Déploiement progressif en 5 phases.",
        "mod08Num": "MOD_08",
        "mod08Name": "Gestion de crise",
        "mod08Desc": "Incidents à 3 niveaux. Exercices de kill switch."
      },
      "video": {
        "eyebrow": "// Pourquoi ACF",
        "title": "La gouvernance ne peut pas attendre.\nLes agents décident déjà.",
        "description1": "En 2026, les agents autonomes exécutent déjà des décisions en environnement commercial — fixation des prix, qualification des leads, traitement des réclamations, gestion des contrats. La plupart des organisations n'ont aucun cadre pour les gouverner.",
        "description2": "ACF a été créé pour combler ce vide — avant qu'une défaillance de gouvernance ne devienne une crise juridique, financière ou réputationnelle.",
        "quote": "\"La question n'est plus de savoir s'il faut déployer des agents. C'est comment les déployer sans abandonner votre souveraineté.\"",
        "quoteAuthor": "— Vincent DORANGE, Créateur du Standard ACF",
        "thumbnailBadge": "ACF — MESSAGE DU FONDATEUR",
        "thumbnailName": "Vincent DORANGE",
        "thumbnailRole": "Créateur, Agentic Commerce Framework®",
        "duration": "3:09",
        "stat1Value": "2026",
        "stat1Label": "Version officielle",
        "stat2Value": "45p",
        "stat2Label": "Documentation complète",
        "stat3Value": "INPI",
        "stat3Label": "Juridiquement protégé",
        "videoModalPlaceholder": "ESPACE VIDÉO",
        "videoModalTitle": "Téléchargez votre vidéo pour activer la lecture",
        "videoModalDesc": "Remplacez ce modal par une URL d'intégration YouTube ou Vimeo dans le code"
      },
      "products": {
        "eyebrow": "// Écosystème",
        "title": "L'écosystème ACF",
        "description": "Trois produits complémentaires opérationnalisant le Standard ACF.",
        "score": {
          "label": "OUTIL DIAGNOSTIQUE",
          "title": "ACF Score",
          "description": "Score de souveraineté propriétaire mesurant votre indépendance décisionnelle selon 6 dimensions de gouvernance.",
          "feat1": "Métrique composite du Score de souveraineté",
          "feat2": "Visualisation radar à 6 axes",
          "feat3": "Plan d'action personnalisé par axe",
          "link": "Mesurez votre Score →"
        },
        "control": {
          "label": "PLATEFORME SAAS",
          "title": "ACF Control",
          "description": "Tableau de bord de gouvernance en temps réel surveillant vos 18 KPIs de souveraineté avec gating adaptatif et escalade automatisée.",
          "feat1": "18 KPIs selon 6 axes de gouvernance",
          "feat2": "Gating adaptatif avec escalade humaine",
          "feat3": "Logs d'audit inaltérables",
          "link": "Découvrir ACF Control →"
        },
        "certification": {
          "label": "ATTESTATION INDÉPENDANTE",
          "title": "Certification ACF",
          "description": "Certification indépendante attestant la conformité au standard de gouvernance ACF. Publiquement vérifiable.",
          "feat1": "Parcours de certification niveaux 1, 2 et 3",
          "feat2": "Badge publiquement vérifiable",
          "feat3": "Renouvellement annuel + surveillance continue",
          "link": "Obtenez la certification →"
        }
      },
      "blog": {
        "eyebrow": "// Analyses",
        "title": "Dernières publications du blog ACF",
        "description": "Analyses de gouvernance, mises à jour du framework et recherche en intelligence agentique.",
        "article1": {
          "category": "RÉGLEMENTATION IA",
          "title": "Comment l'AI Act européen s'applique aux systèmes agentiques en 2026",
          "excerpt": "L'approche basée sur les risques de l'AI Act crée des obligations spécifiques pour les agents autonomes. Voici ce que couvre la gouvernance ACF Niveau 2.",
          "date": "2026-02-15",
          "readMore": "Lire →"
        },
        "article2": {
          "category": "GOUVERNANCE",
          "title": "Le DDA : Pourquoi chaque entreprise IA-native a besoin d'un Délégué à la Décision Agentique",
          "excerpt": "Le DDA est le gardien légal de vos agents autonomes. Comment créer et renforcer ce rôle essentiel.",
          "date": "2026-02-08",
          "readMore": "Lire →"
        },
        "article3": {
          "category": "TECHNIQUE",
          "title": "Concevoir un Kill Switch à trois niveaux pour les systèmes d'agents autonomes",
          "excerpt": "Un kill switch efficace n'est pas un simple bouton. ACF spécifie trois niveaux d'interruption avec des temps de réponse définis.",
          "date": "2026-01-29",
          "readMore": "Lire →"
        },
        "viewAll": "Voir tous les articles →"
      },
      "cta": {
        "eyebrow": "// Prochaine étape",
        "watermark": "ACF®",
        "title": "Prêt à gouverner vos\nsystèmes agentiques ?",
        "description": "Demandez une évaluation de gouvernance et découvrez votre Score de souveraineté actuel.",
        "ctaPrimary": "Demander une évaluation de gouvernance →",
        "ctaSecondary": "Devenir partenaire ACF"
      },
      "aiWidget": {
        "buttonLabel": "Demandez à l'agent ACF",
        "buttonStatus": "GOUVERNANCE IA · EN LIGNE",
        "modalBeta": "BÊTA",
        "modalTitle": "Demandez à ACF",
        "modalSubtitle": "Un chatbot répondant aux questions sur le Standard ACF et les analyses de gouvernance",
        "inputPlaceholder": "Posez une question sur la gouvernance ACF...",
        "trendingLabel": "QUESTIONS TENDANCE",
        "question1": "Qu'est-ce que le Standard ACF ?",
        "question2": "Comment obtenir la certification ACF ?",
        "question3": "Qu'est-ce que le rôle du DDA ?",
        "question4": "Qu'est-ce que le Score de souveraineté ?",
        "question5": "Les 4 Principes fondateurs ?",
        "disclaimer": "Expérience IA. Réponses basées sur la documentation du Standard ACF.",
        "disclaimerLink": "En savoir plus"
      },
      "footer": {
        "logoAbbr": "ACF",
        "logoName": "Agentic Commerce Framework®",
        "logoSubtitle": "Standard mondial pour la gouvernance de l'IA",
        "description": "Le standard de gouvernance de référence pour les organisations déployant des systèmes agentiques autonomes. Protégé — Loi n° 2018-670.",
        "frameworkTitle": "Framework",
        "frameworkLinks": {
          "theStandard": "Le Standard",
          "methodology": "Méthodologie",
          "research": "Recherche",
          "acfCertification": "Certification ACF"
        },
        "productsTitle": "Produits",
        "productsLinks": {
          "acfScore": "ACF Score",
          "acfControl": "ACF Control",
          "certification": "Certification",
          "academy": "Academy"
        },
        "organizationTitle": "Organisation",
        "organizationLinks": {
          "partnerPortal": "Portail partenaire",
          "about": "À propos",
          "contact": "Contact",
          "legal": "Mentions légales"
        },
        "copyright": "© 2026 Agentic Commerce Framework® — Vincent DORANGE. Tous droits réservés. Enregistré INPI.",
        "privacy": "Confidentialité",
        "terms": "Conditions",
        "cookies": "Cookies"
      }
    }
  }
}