{"meta":{"language":"PL","languageCode":"pl","locale":"pl-PL"},"common":{"readMore":"Czytaj więcej","learnMore":"Dowiedz się więcej","getStarted":"Zacznij","downloadPDF":"Pobierz PDF","watchVideo":"Zobacz wideo","close":"Zamknij","open":"Otwórz","loading":"Ładowanie","backToHome":"Powrót do strony głównej","menu":"Menu"},"regionSelector":{"title":"Wybierz swój region i język","close":"✕ Zamknij","global":"Globalny (Angielski)","northAmerica":"Ameryka Północna","latinAmerica":"Ameryka Łacińska","westernEurope":"Europa Zachodnia","nordicBaltic":"Kraje Nordyckie i Bałtyckie","centralEasternEurope":"Europa Środkowo-Wschodnia","middleEastAfrica":"Bliski Wschód i Afryka","asiaPacific":"Azja i Pacyfik"},"nav":{"menu":"Menu","logoText":"Agentic Commerce Framework®","logoSubtext":"Globalny Standard Zarządzania AI","region":"GLOBALNY | PL","theStandard":"Standard","acfScore":"ACF Score","acfControl":"ACF Control","acfCertification":"Certyfikacja ACF","partners":"Partnerzy","requestAssessment":"Poproś o ocenę","partnerLogin":"Logowanie Partnera","applyPartner":"Zostań Partnerem","contact":"Kontakt"},"megaMenu":{"framework":{"title":"Framework","link":"Standard ACF →","subtitle":"Ostateczna metodologia zarządzania dla systemów agentycznych w środowiskach komercyjnych.","architecture":{"title":"Architektura","principles":"4 Podstawowe Zasady","layers":"4 Warstwy Operacyjne","maturity":"4 Poziomy Dojrzałości"},"methodology":{"title":"Metodologia","modules":"8 Modułów Wdrożeniowych","constitution":"Konstytucja Agentyczna","dda":"Ramowy Rola DDA","killSwitch":"Protokół Kill Switch"},"featured":{"label":"WYRÓŻNIONE","whitepaper":{"title":"Pobierz Białą Księgę ACF","description":"Pełna specyfikacja — bezpłatnie dla zarejestrowanych użytkowników."},"release":{"title":"ACF v1.0 — Luty 2026","description":"Oficjalne wydanie. Co nowego w frameworku."}}},"products":{"title":"Produkty","link":"Produkty →","subtitle":"Trzy narzędzia operacjonalizujące Standard ACF w Twojej organizacji.","diagnostic":{"title":"Diagnostyka","score":"ACF Score — Metryka Suwerenności","methodology":"Metodologia Punktacji","axes":"6 Osi Zarządzania"},"saas":{"title":"Platforma SaaS","control":"ACF Control — Panel Zarządzania","kpis":"18 KPI Suwerenności","gating":"Adaptacyjny System Bramkowania"},"certification":{"title":"Certyfikacja","program":"Program Certyfikacji ACF","levels":"Poziomy Certyfikacji","audit":"Proces Audytu"}},"resources":{"title":"Zasoby","link":"Zasoby →","subtitle":"Wgląd w zarządzanie, badania i dokumentacja techniczna.","insights":{"title":"Najnowsze Spostrzeżenia","aiAct":"AI Act UE i Systemy Agentyczne","dda":"Rola DDA Wyjaśniona","killSwitch":"Projektowanie 3-Poziomowego Kill Switch"},"documentation":{"title":"Dokumentacja","specs":"Specyfikacje Techniczne","research":"Publikacje Badawcze","academy":"ACF Academy"}},"about":{"title":"O ACF","link":"O ACF →","subtitle":"Historia, misja i ochrona prawna za Agentic Commerce Framework®.","whoWeAre":{"title":"Kim Jesteśmy","vincent":"Vincent DORANGE — Twórca","mission":"Misja i Wartości","legal":"Ochrona Prawna (INPI)"},"howWeWork":{"title":"Jak Pracujemy","network":"Sieć Praktyków","audit":"Audyt i Certyfikacja","contact":"Skontaktuj się"},"registered":{"label":"ZAREJESTROWANE","title":"Chronione INPI — Loi n° 2018-670","description":"ACF® jest znakiem towarowym. Cała metodologia i narzędzia są prawnie chronione."}},"partners":{"title":"Partnerzy","link":"Partnerzy →","subtitle":"Dołącz do sieci Praktyków ACF i oferuj usługi zarządzania swoim klientom.","portal":{"title":"Portal Partnerski","login":"Zaloguj się do Portalu Partnerskiego","dashboard":"Panel i Narzędzia","training":"Materiały Szkoleniowe","toolkit":"Zestaw Narzędzi Praktyka ACF"},"become":{"title":"Zostań Partnerem","apply":"Aplikuj","tiers":"Poziomy Partnerstwa","certified":"Najpierw Uzyskaj Certyfikację ACF"}},"user":{"partnerAccess":"Dostęp Partnera","partnerLogin":"Logowanie Partnera","applyPartner":"Zostań Partnerem","contact":"Kontakt"}},"hero":{"title":"Globalny Standard dla","typing":{"word1":"Zarządzania","word2":"Suwerenności","word3":"Inteligencji","word4":"Handlu"},"description":"Agentic Commerce Framework® (ACF) to ostateczna metodologia zarządzania dla wdrażania, nadzorowania i kontrolowania autonomicznych systemów agentycznych w środowiskach komercyjnych.","cta":{"primary":"Poproś o Ocenę Zarządzania →","secondary":"Przeczytaj Standard"},"stats":{"principles":{"value":"4","label":"Podstawowe<br>Zasady"},"modules":{"value":"8","label":"Moduły<br>Wdrożeniowe"},"kpis":{"value":"18","label":"KPI<br>Suwerenności"},"tools":{"value":"17","label":"Narzędzia<br>Własnościowe"}},"satellites":{"score":{"name":"ACF Score","description":"Metryka Suwerenności"},"control":{"name":"ACF Control","description":"SaaS Zarządzania"},"certification":{"name":"Certyfikacja","description":"Poświadczenie"},"partners":{"name":"Partnerzy","description":"Praktycy"}}},"statsBar":{"layers":{"value":"4","label":"Warstwy Operacyjne"},"kpis":{"value":"18","label":"KPI Suwerenności"},"tools":{"value":"17","label":"Narzędzia Własnościowe"},"sovereignty":{"value":"100","suffix":"%","label":"Suwerenność Ludzka"}},"principles":{"badge":"// Architektura","title":"4 Podstawowe Zasady","subtitle":"Cztery niezmienne aksjomaty definiujące granicę między ludzkim autorytetem a autonomicznym wykonaniem agenta.","principle1":{"number":"01","title":"Suwerenność Decyzyjna","description":"Krytyczne decyzje strategiczne nigdy nie są delegowane do autonomicznych agentów."},"principle2":{"number":"02","title":"Zarządzanie przez Projektowanie","description":"Ramy zarządzania są definiowane przed wdrożeniem, nie po."},"principle3":{"number":"03","title":"Ostateczna Kontrola Ludzka","description":"Każdy system agentyczny musi zachować możliwość ludzkiej interwencji."},"principle4":{"number":"04","title":"Śledzona Odpowiedzialność","description":"Każde autonomiczne działanie musi być audytowalne i przypisywalne."}},"layers":{"badge":"// Struktura","title":"4 Warstwy Operacyjne","subtitle":"Hierarchiczna architektura od strategicznego zarządzania do nadzoru wykonania w czasie rzeczywistym.","layer1":{"number":"LAYER_01","title":"Zarządzanie i Suwerenność","description":"Karta suwerenności, komitet zarządzania, macierz RACI, mapa stref niedelegowanych."},"layer2":{"number":"LAYER_02","title":"Polityka Decyzyjna","description":"Ważone cele, reguły arbitrażu, progi eskalacji, ograniczenia regulacyjne."},"layer3":{"number":"LAYER_03","title":"System Agentów","description":"Wyraźny mandat na agenta, perimetr interakcji, poziom autonomii, taksonomia 5 kategorii."},"layer4":{"number":"LAYER_04","title":"Wykonanie i Nadzór","description":"Adaptacyjna macierz bramkowania, alerty wielopoziomowe, 18 KPI suwerenności, panele na żywo."}},"maturity":{"badge":"// Progresja","title":"4 Poziomy Dojrzałości Agentycznej","subtitle":"ACF klasyfikuje systemy według poziomu autonomii. Poziom 2 jest zalecanym celem wdrożenia.","level0":{"code":"POZIOM_0","name":"Klasyczna Automatyzacja","risk":"Bardzo Niskie Ryzyko","description":"Stałe reguły, brak ML. Ludzka interwencja przy każdej modyfikacji."},"level1":{"code":"POZIOM_1","name":"Wspomagani Agenci","risk":"Niskie Ryzyko","description":"Agenci analizują i rekomendują. Każda ostateczna decyzja pozostaje przy człowieku."},"level2":{"code":"POZIOM_2","name":"Zarządzani Agenci","risk":"Umiarkowane Ryzyko","description":"Agenci decydują w ramach ścisłego zarządzania. Strefy niedelegowane zablokowane.","badge":"★ Zalecany Cel"},"level3":{"code":"POZIOM_3","name":"Nadzorowana Autonomia","risk":"Wysokie Ryzyko","description":"Agenci decydują i uczą się. Maksymalne zarządzanie. Tylko dla dojrzałych organizacji."}},"modules":{"badge":"// Metodologia","title":"8 Modułów Wdrożeniowych","subtitle":"Sekwencyjna ścieżka wdrażana progresywnie przez 6-18 miesięcy. Każdy moduł opiera się na poprzednim.","module1":{"code":"MOD_01","name":"Diagnoza Suwerenności","description":"Obliczanie Wyniku Suwerenności. Mapowanie stref ryzyka."},"module2":{"code":"MOD_02","name":"Mapowanie Decyzyjne","description":"Macierz Krytyczności. Strefy niedelegowane."},"module3":{"code":"MOD_03","name":"Konstytucja Agentyczna","description":"9 artykułów. Podpisana przez komitet zarządzania."},"module4":{"code":"MOD_04","name":"Projektowanie Systemu Agentów","description":"Arkusze mandatów, perimetry interakcji."},"module5":{"code":"MOD_05","name":"Bezpieczeństwo i Odwracalność","description":"Sandboxing, plan odwracalności. Projekt kill switch."},"module6":{"code":"MOD_06","name":"Ciągłe Zarządzanie","description":"Comiesięczne przeglądy. Roczny audyt zgodności."},"module7":{"code":"MOD_07","name":"Mapa Drogowa Wdrożenia","description":"Progresywne wdrożenie w 5 fazach."},"module8":{"code":"MOD_08","name":"Zarządzanie Kryzysowe","description":"Incydenty 3-poziomowe. Ćwiczenia kill switch."}},"video":{"badge":"// Dlaczego ACF","title":"Zarządzanie Nie Może Czekać.<br>Agenci Już Decydują.","description1":"W 2026 roku autonomiczni agenci już wykonują decyzje w środowiskach komercyjnych — ustalanie cen, kwalifikacja leadów, przetwarzanie roszczeń, zarządzanie kontraktami. Większość organizacji nie ma ram do ich zarządzania.","description2":"ACF powstało, aby wypełnić tę lukę — zanim awaria zarządzania stanie się kryzysem prawnym, finansowym lub reputacyjnym.","quote":{"text":"Pytanie nie brzmi już <em>czy</em> wdrażać agentów. To <em>jak</em> je wdrażać bez oddawania swojej suwerenności.","author":"— Vincent DORANGE, Twórca Standardu ACF"},"player":{"badge":"ACF — WIADOMOŚĆ ZAŁOŻYCIELA","name":"Vincent DORANGE","role":"Twórca, Agentic Commerce Framework®","duration":"3:09"},"stats":{"release":{"value":"2026","label":"Oficjalne Wydanie"},"documentation":{"value":"45s","label":"Pełna Dokumentacja"},"protection":{"value":"INPI","label":"Prawnie Chronione"}},"modal":{"placeholder":"PLACEHOLDER WIDEO","title":"Prześlij swoje wideo, aby włączyć odtwarzanie","description":"Zastąp tę modalną adresem URL osadzania YouTube lub Vimeo w kodzie"}},"products":{"badge":"// Ekosystem","title":"Ekosystem ACF","subtitle":"Trzy komplementarne produkty operacjonalizujące Standard ACF.","score":{"label":"NARZĘDZIE DIAGNOSTYCZNE","title":"ACF Score","description":"Własnościowy Wynik Suwerenności mierzący Twoją niezależność decyzyjną w 6 wymiarach zarządzania.","features":{"feature1":"Złożona metryka Wyniku Suwerenności","feature2":"Wizualizacja radarowa 6-osiowa","feature3":"Spersonalizowany plan działania na oś"},"cta":"Zmierz swój Wynik →"},"control":{"label":"PLATFORMA SAAS","title":"ACF Control","description":"Panel zarządzania w czasie rzeczywistym monitorujący Twoje 18 KPI Suwerenności z adaptacyjnym bramkowaniem i automatyczną eskalacją.","features":{"feature1":"18 KPI na 6 osiach zarządzania","feature2":"Adaptacyjne bramkowanie z ludzką eskalacją","feature3":"Dzienniki audytu odporne na manipulację"},"cta":"Odkryj ACF Control →"},"certification":{"label":"NIEZALEŻNE POŚWIADCZENIE","title":"Certyfikacja ACF","description":"Niezależna certyfikacja poświadczająca zgodność ze standardem zarządzania ACF. Publicznie weryfikowalna.","features":{"feature1":"Ścieżki certyfikacji Poziom 1, 2 i 3","feature2":"Publicznie weryfikowalna odznaka","feature3":"Coroczne odnowienie + ciągły monitoring"},"cta":"Uzyskaj Certyfikację →"}},"blog":{"badge":"// Spostrzeżenia","title":"Najnowsze z Bloga ACF","subtitle":"Spostrzeżenia dotyczące zarządzania, aktualizacje frameworku i badania nad inteligencją agentyczną.","article1":{"category":"REGULACJA AI","title":"Jak AI Act UE Dotyczy Systemów Agentycznych w 2026","excerpt":"Podejście oparte na ryzyku AI Act tworzy specyficzne obowiązki dla autonomicznych agentów. Oto co obejmuje zarządzanie ACF Poziom 2.","date":"2026-02-15","cta":"Czytaj →"},"article2":{"category":"ZARZĄDZANIE","title":"DDA: Dlaczego Każda Firma Natywna AI Potrzebuje Pełnomocnika ds. Agentów Decyzyjnych","excerpt":"DDA jest prawnym opiekunem Twoich autonomicznych agentów. Jak stworzyć i wzmocnić tę krytyczną rolę.","date":"2026-02-08","cta":"Czytaj →"},"article3":{"category":"TECHNICZNE","title":"Projektowanie Trzypoziomowego Kill Switch dla Autonomicznych Systemów Agentycznych","excerpt":"Skuteczny kill switch to nie pojedynczy przycisk. ACF określa trzy poziomy przerwania z zdefiniowanymi czasami reakcji.","date":"2026-01-29","cta":"Czytaj →"},"viewAll":"Zobacz Wszystkie Artykuły →"},"cta":{"watermark":"ACF®","badge":"// Następny Krok","title":"Gotowy do Zarządzania<br>Swoimi Systemami Agentycznymi?","description":"Poproś o ocenę zarządzania i odkryj swój obecny Wynik Suwerenności.","primary":"Poproś o Ocenę Zarządzania →","secondary":"Zostań Partnerem ACF"},"footer":{"logoText":"Agentic Commerce Framework®","logoSubtext":"Globalny Standard Zarządzania AI","description":"Ostateczny standard zarządzania dla organizacji wdrażających autonomiczne systemy agentyczne. Chronione — Loi n° 2018-670.","framework":{"title":"Framework","theStandard":"Standard","methodology":"Metodologia","research":"Badania","certification":"Certyfikacja ACF"},"products":{"title":"Produkty","score":"ACF Score","control":"ACF Control","certification":"Certyfikacja","academy":"Academy"},"organization":{"title":"Organizacja","partnerPortal":"Portal Partnerski","about":"O Nas","contact":"Kontakt","legal":"Prawne"},"copyright":"© 2026 Agentic Commerce Framework® — Vincent DORANGE. Wszelkie prawa zastrzeżone. Zarejestrowane INPI.","legal":{"privacy":"Prywatność","terms":"Warunki","cookies":"Ciasteczka"}},"ai":{"button":{"label":"Zapytaj Agenta ACF","status":"ZARZĄDZANIE AI · ONLINE"},"modal":{"close":"×","beta":"BETA","title":"Zapytaj ACF","subtitle":"Chatbot odpowiadający na pytania na podstawie Standardu ACF i spostrzeżeń dotyczących zarządzania","placeholder":"Zapytaj o zarządzanie ACF...","send":"Wyślij","trending":{"label":"POPULARNE PYTANIA","q1":"Czym jest Standard ACF?","q2":"Jak uzyskać certyfikację ACF?","q3":"Czym jest rola DDA?","q4":"Czym jest Wynik Suwerenności?","q5":"4 Podstawowe Zasady?"},"disclaimer":"Eksperyment AI. Odpowiedzi oparte na dokumentacji Standardu ACF.","seeMore":"Dowiedz Się Więcej"}}}
